merlin/__init__.py
merlin/ascii_art.py
merlin/celery.py
merlin/display.py
merlin/log_formatter.py
merlin/main.py
merlin/router.py
merlin/utils.py
merlin/cli/__init__.py
merlin/cli/argparse_main.py
merlin/cli/utils.py
merlin/cli/commands/__init__.py
merlin/cli/commands/command_entry_point.py
merlin/cli/commands/config.py
merlin/cli/commands/example.py
merlin/cli/commands/info.py
merlin/cli/commands/monitor.py
merlin/cli/commands/purge.py
merlin/cli/commands/query_workers.py
merlin/cli/commands/queue_info.py
merlin/cli/commands/restart.py
merlin/cli/commands/run.py
merlin/cli/commands/run_workers.py
merlin/cli/commands/server.py
merlin/cli/commands/status.py
merlin/cli/commands/stop_workers.py
merlin/common/__init__.py
merlin/common/dumper.py
merlin/common/enums.py
merlin/common/sample_index.py
merlin/common/sample_index_factory.py
merlin/common/tasks.py
merlin/common/util_sampling.py
merlin/common/security/__init__.py
merlin/common/security/encrypt.py
merlin/common/security/encrypt_backend_traffic.py
merlin/config/__init__.py
merlin/config/broker.py
merlin/config/celeryconfig.py
merlin/config/config_filepaths.py
merlin/config/configfile.py
merlin/config/merlin_config_manager.py
merlin/config/results_backend.py
merlin/config/utils.py
merlin/data/celery/__init__.py
merlin/data/celery/app.yaml
merlin/data/celery/app_redis.yaml
merlin/examples/__init__.py
merlin/examples/examples.py
merlin/examples/generator.py
merlin/examples/dev_workflows/bad_format1.yaml
merlin/examples/dev_workflows/bad_format10.yaml
merlin/examples/dev_workflows/bad_format11.yaml
merlin/examples/dev_workflows/bad_format2.yaml
merlin/examples/dev_workflows/bad_format3.yaml
merlin/examples/dev_workflows/bad_format4.yaml
merlin/examples/dev_workflows/bad_format5.yaml
merlin/examples/dev_workflows/bad_format6.yaml
merlin/examples/dev_workflows/bad_format7.yaml
merlin/examples/dev_workflows/bad_format8.yaml
merlin/examples/dev_workflows/bad_format9.yaml
merlin/examples/dev_workflows/full_format.yaml
merlin-1.13.0.dist-info/licenses/LICENSE
merlin-1.13.0.dist-info/METADATA
merlin-1.13.0.dist-info/WHEEL
merlin-1.13.0.dist-info/entry_points.txt
merlin-1.13.0.dist-info/top_level.txt
merlin-1.13.0.dist-info/RECORD
