Metadata-Version: 2.4
Name: merlin
Version: 1.13.0
Summary: The building blocks of workflows!
Home-page: https://github.com/LLNL/merlin
Author: Merlin Dev team
Author-email: merlin@llnl.gov
License: MIT
Keywords: machine learning workflow
Classifier: Programming Language :: Python :: 3.8
Classifier: Programming Language :: Python :: 3.9
Classifier: Programming Language :: Python :: 3.10
Classifier: Programming Language :: Python :: 3.11
Classifier: Programming Language :: Python :: 3.12
Classifier: Programming Language :: Python :: 3.13
License-File: LICENSE
Requires-Dist: cached_property
Requires-Dist: celery[redis,sqlalchemy]>=5.0.3
Requires-Dist: coloredlogs
Requires-Dist: cryptography
Requires-Dist: maestrowf>=1.1.9dev1
Requires-Dist: numpy
Requires-Dist: parse
Requires-Dist: psutil>=5.1.0
Requires-Dist: pyyaml>=5.1.2
Requires-Dist: setuptools
Requires-Dist: tabulate
Requires-Dist: redis>=4.3.4
Provides-Extra: dev
Requires-Dist: build; extra == "dev"
Requires-Dist: black; extra == "dev"
Requires-Dist: dep-license; extra == "dev"
Requires-Dist: flake8; extra == "dev"
Requires-Dist: isort; extra == "dev"
Requires-Dist: pytest; extra == "dev"
Requires-Dist: pytest-cov; extra == "dev"
Requires-Dist: pylint; extra == "dev"
Requires-Dist: twine; extra == "dev"
Requires-Dist: sphinx>=2.0.0; extra == "dev"
Requires-Dist: alabaster; extra == "dev"
Requires-Dist: johnnydep; extra == "dev"
Requires-Dist: deepdiff; extra == "dev"
Requires-Dist: orderly-set==5.3.0; python_version == "3.8" and extra == "dev"
Requires-Dist: pytest-order; extra == "dev"
Requires-Dist: pytest-mock; extra == "dev"
Dynamic: author
Dynamic: author-email
Dynamic: classifier
Dynamic: description
Dynamic: description-content-type
Dynamic: home-page
Dynamic: keywords
Dynamic: license
Dynamic: license-file
Dynamic: provides-extra
Dynamic: requires-dist
Dynamic: summary
